[
  {
    "id": 1,
    "nombre": "Carlos Arturo Serrano Rodriguez",
    "documento": "6759525",
    "telefono": "3107981224",
    "email": "csrodriguez2011@gmail.com"
  },
  {
    "id": 2,
    "nombre": "Laura Marcela Diaz Salcedo",
    "documento": "1053616703",
    "telefono": "3208849093",
    "email": "lauradiaz.salcedo04@gmail.com"
  },
  {
    "id": 3,
    "nombre": "Mayerline Maidi Tarazona Miranda",
    "documento": "27601972",
    "telefono": "3124680833",
    "email": "tarazonamayito5@gmail.com"
  },
  {
    "id": 4,
    "nombre": "Jeixon Ovelio Arias Guerra",
    "documento": "1049637093",
    "telefono": "3204708086",
    "email": ""
  }
]
